CalcDSSB/__init__.py
CalcDSSB-0.1.3.dist-info/WHEEL
CalcDSSB-0.1.3.dist-info/METADATA
CalcDSSB-0.1.3.dist-info/RECORD
