Metadata-Version: 2.1
Name: CalcDSSB
Version: 0.1.3
Summary: Calculator package
Author: Simas B
Author-email: test@test.test
Classifier: License :: OSI Approved :: MIT License
